__init__.py
android_controller/__init__.py
android_controller/controller.py
android_controller/device.py
PyDroidCTRL-1.2.1.dist-info/LICENSE
PyDroidCTRL-1.2.1.dist-info/METADATA
PyDroidCTRL-1.2.1.dist-info/WHEEL
PyDroidCTRL-1.2.1.dist-info/top_level.txt
PyDroidCTRL-1.2.1.dist-info/RECORD
