Metadata-Version: 2.1
Name: PyDroidCTRL
Version: 1.2.1
Summary: Control android with python
Author-email: XoQ <xoq2988@proton.me>
License: MIT
Project-URL: Homepage, https://github.com/XoQ2988/android_controller
Keywords: python,android,adb
Classifier: Programming Language :: Python :: 3
Classifier: License :: OSI Approved :: MIT License
Classifier: Operating System :: Microsoft
Requires-Python: >=3.7
License-File: LICENSE
